src/main.py
src/mysql.py
pymysql_json_cli-0.0.1.dist-info/entry_points.txt
pymysql_json_cli-0.0.1.dist-info/WHEEL
pymysql_json_cli-0.0.1.dist-info/METADATA
pymysql_json_cli-0.0.1.dist-info/RECORD
